Metadata-Version: 2.1
Name: bigcummies
Version: 0.0.1
Summary: big cummies by Bruham
Home-page: https://github.com/Bruham1/bigcummies
Author: Bruham
Author-email: chaininelol@gmail.com
License: MIT
Download-URL: https://github.com/Bruham1/bigcummies/archive/v0.0.1.zip
Keywords: big,cum,cummies
Platform: UNKNOWN
Classifier: Development Status :: 3 - Alpha
Classifier: Intended Audience :: Education
Classifier: Topic :: Utilities
Classifier: License :: OSI Approved :: MIT License
Classifier: Programming Language :: Python :: 3
Classifier: Programming Language :: Python :: 3.4
Classifier: Programming Language :: Python :: 3.5
Classifier: Programming Language :: Python :: 3.6
Classifier: Programming Language :: Python :: 3.7
Classifier: Programming Language :: Python :: 3.8
Classifier: Programming Language :: Python :: 3.9
License-File: LICENSE.txt
